pydarknet/pydarknet_helpers.py
pydarknet/__main__.py
pydarknet/_pydarknet.py
pydarknet/_version.py
pydarknet/__init__.py
pydarknet/ctypes_interface.py
pydarknet/lib/libpydarknet.so
pydarknet/lib/libpydarknet.so.4.0.0
pydarknet/lib/libpydarknet.so.4.0
pydarknet/lib/libpydarknet_s.a
wbia_pydarknet-4.0.0.dist-info/LICENSE
wbia_pydarknet-4.0.0.dist-info/RECORD
wbia_pydarknet-4.0.0.dist-info/top_level.txt
wbia_pydarknet-4.0.0.dist-info/WHEEL
wbia_pydarknet-4.0.0.dist-info/METADATA
